{
  "version": "7",
  "dialect": "postgresql",
  "entries": [
    {
      "idx": 0,
      "version": "7",
      "when": 1767738858967,
      "tag": "0000_common_drax",
      "breakpoints": true
    },
    {
      "idx": 1,
      "version": "7",
      "when": 1740865200000,
      "tag": "0001_realtor_growth_engine",
      "breakpoints": true
    },
    {
      "idx": 2,
      "version": "7",
      "when": 1774582083000,
      "tag": "0002_ghl_sync",
      "breakpoints": true
    },
    {
      "idx": 3,
      "version": "7",
      "when": 1774848000000,
      "tag": "0003_users_entitlement_columns",
      "breakpoints": true
    },
    {
      "idx": 4,
      "version": "7",
      "when": 1775000000000,
      "tag": "0004_message_media_persistence",
      "breakpoints": true
    }
  ]
}
